aoc_lube/__init__.py
aoc_lube/__main__.py
aoc_lube/code_template.txt
aoc_lube/utils.py
aoc_lube-1.3.2.dist-info/LICENSE
aoc_lube-1.3.2.dist-info/METADATA
aoc_lube-1.3.2.dist-info/WHEEL
aoc_lube-1.3.2.dist-info/top_level.txt
aoc_lube-1.3.2.dist-info/RECORD
