Metadata-Version: 2.1
Name: aoc_lube
Version: 1.3.2
Summary: Proper Advent of Code lubricant.
Author-email: salt-die <salt-die@protonmail.com>
License: Unlicense
Project-URL: repository, https://github.com/salt-die/aoc_lube
Classifier: Programming Language :: Python :: 3
Classifier: Operating System :: OS Independent
Requires-Python: >=3.12
License-File: LICENSE
Requires-Dist: beautifulsoup4>=4.12.2
Requires-Dist: requests>=2.31.0
Requires-Dist: tomlkit>=0.12.3
Provides-Extra: utils
Requires-Dist: networkx>=3.2.1; extra == "utils"
Requires-Dist: numpy>=1.26.0; extra == "utils"
